brapi/__init__.py
brapi/_base_client.py
brapi/_client.py
brapi/_compat.py
brapi/_constants.py
brapi/_exceptions.py
brapi/_files.py
brapi/_models.py
brapi/_qs.py
brapi/_resource.py
brapi/_response.py
brapi/_streaming.py
brapi/_types.py
brapi/_version.py
brapi/py.typed
brapi/_utils/__init__.py
brapi/_utils/_compat.py
brapi/_utils/_datetime_parse.py
brapi/_utils/_logs.py
brapi/_utils/_proxy.py
brapi/_utils/_reflection.py
brapi/_utils/_resources_proxy.py
brapi/_utils/_streams.py
brapi/_utils/_sync.py
brapi/_utils/_transform.py
brapi/_utils/_typing.py
brapi/_utils/_utils.py
brapi/lib/.keep
brapi/resources/__init__.py
brapi/resources/available.py
brapi/resources/quote.py
brapi/resources/v2/__init__.py
brapi/resources/v2/crypto.py
brapi/resources/v2/currency.py
brapi/resources/v2/inflation.py
brapi/resources/v2/prime_rate.py
brapi/resources/v2/v2.py
brapi/types/__init__.py
brapi/types/available_list_params.py
brapi/types/available_list_response.py
brapi/types/balance_sheet_entry.py
brapi/types/cashflow_entry.py
brapi/types/default_key_statistics_entry.py
brapi/types/financial_data_entry.py
brapi/types/income_statement_entry.py
brapi/types/quote_list_params.py
brapi/types/quote_list_response.py
brapi/types/quote_retrieve_params.py
brapi/types/quote_retrieve_response.py
brapi/types/value_added_entry.py
brapi/types/v2/__init__.py
brapi/types/v2/crypto_list_available_params.py
brapi/types/v2/crypto_list_available_response.py
brapi/types/v2/crypto_retrieve_params.py
brapi/types/v2/crypto_retrieve_response.py
brapi/types/v2/currency_list_available_params.py
brapi/types/v2/currency_list_available_response.py
brapi/types/v2/currency_retrieve_params.py
brapi/types/v2/currency_retrieve_response.py
brapi/types/v2/inflation_list_available_params.py
brapi/types/v2/inflation_list_available_response.py
brapi/types/v2/inflation_retrieve_params.py
brapi/types/v2/inflation_retrieve_response.py
brapi/types/v2/prime_rate_list_available_params.py
brapi-1.1.0.dist-info/METADATA
brapi-1.1.0.dist-info/WHEEL
brapi-1.1.0.dist-info/licenses/LICENSE
brapi-1.1.0.dist-info/RECORD
